asynchttp/__init__.py
asynchttp/client.py
asynchttp/enums.py
multifuncpy-0.1.1.dist-info/METADATA
multifuncpy-0.1.1.dist-info/WHEEL
multifuncpy-0.1.1.dist-info/top_level.txt
multifuncpy-0.1.1.dist-info/RECORD
