Metadata-Version: 2.1
Name: multifuncpy
Version: 0.1.1
Summary: A simple async HTTP client based on aiohttp
Home-page: https://github.com/wieszheng
Author: shweZheng
Author-email: shiweisai@gmail.com
Classifier: Development Status :: 4 - Beta
Classifier: Intended Audience :: Developers
Classifier: License :: OSI Approved :: MIT License
Classifier: Operating System :: OS Independent
Classifier: Programming Language :: Python :: 3
Classifier: Programming Language :: Python :: 3.12
Classifier: Topic :: Internet :: WWW/HTTP
Requires-Python: >=3.7
Requires-Dist: aiohttp>=3.8.0
